{
  "sources": [
    {
      "title": "悪の秘密ぼっち「ヘライザー総統」と言う名のファンタジー",
      "feedUrl": "https://www.youtube.com/feeds/videos.xml?channel_id=UCOOt1AsvDZoav6XjN6Tly1g",
      "siteUrl": "https://www.youtube.com/channel/UCOOt1AsvDZoav6XjN6Tly1g",
      "articles": [
        {
          "id": "https://www.youtube.com/watch?v=FVBrkAf-ObY",
          "author": null,
          "description": "",
          "link": "https://www.youtube.com/watch?v=FVBrkAf-ObY",
          "publishedOn": "2021-10-18T17:16:33.000Z",
          "wordCount": null,
          "title": "UUUM鎌田社長・不倫発覚！コレコレ配信中止の理由！FLASH・謎の圧力と株価大暴落 芸能ニュース 無料 芸能 ニュース"
        },
        {
          "id": "https://www.youtube.com/watch?v=ZFeKPtrXsl8",
          "author": null,
          "description": "",
          "link": "https://www.youtube.com/watch?v=ZFeKPtrXsl8",
          "publishedOn": "2021-10-16T19:17:49.000Z",
          "wordCount": null,
          "title": "【閲覧注意】アドラー心理学の嘘・信じちゃいけない目的論・嫌われる勇気のデメリット【ユング原因】やる気・ 哲学  書評"
        },
        {
          "id": "https://www.youtube.com/watch?v=p6WIuYsrsGs",
          "author": null,
          "description": "",
          "link": "https://www.youtube.com/watch?v=p6WIuYsrsGs",
          "publishedOn": "2021-10-13T18:52:23.000Z",
          "wordCount": null,
          "title": "東出昌大の交際発覚！相手の丸の内OL・養育費と杏と唐田えりかの破局と離婚 無料 芸能 ニュース 文春オンライン"
        },
        {
          "id": "https://www.youtube.com/watch?v=PHeDrYfi-n4",
          "author": null,
          "description": "",
          "link": "https://www.youtube.com/watch?v=PHeDrYfi-n4",
          "publishedOn": "2021-10-10T15:54:51.000Z",
          "wordCount": null,
          "title": "東条湖おもちゃ王国・カラクリ迷宮のお城床崩落事故！原因【遊園地・アトラクション・立体迷路【最新時事ニュース tbsnews"
        },
        {
          "id": "https://www.youtube.com/watch?v=8PXHVBu3rPM",
          "author": null,
          "description": "",
          "link": "https://www.youtube.com/watch?v=8PXHVBu3rPM",
          "publishedOn": "2021-10-10T02:31:36.000Z",
          "wordCount": null,
          "title": "佐伯ポインティのwaidanTV・垢バンあるある・垢BAN直前！救いたい【最新時事ニュースYouTuberニュース】"
        },
        {
          "id": "https://www.youtube.com/watch?v=tzoG4Wm0e3w",
          "author": null,
          "description": "",
          "link": "https://www.youtube.com/watch?v=tzoG4Wm0e3w",
          "publishedOn": "2021-10-07T17:30:49.000Z",
          "wordCount": null,
          "title": "大作曲家すぎやまこういち90歳アニソン！代表曲歌います！ゲーム音楽ベスト・アルバム「ドラゴンクエスト」イデオン 訃報"
        },
        {
          "id": "https://www.youtube.com/watch?v=lrS2737inJQ",
          "author": null,
          "description": "",
          "link": "https://www.youtube.com/watch?v=lrS2737inJQ",
          "publishedOn": "2021-10-06T17:52:14.000Z",
          "wordCount": null,
          "title": "Netflixイカゲームが熱い！オマージュ？カイジ・神さまの言うとおり！ぼっち映画女子感想・あらすじ・レビュー 映画紹介"
        },
        {
          "id": "https://www.youtube.com/watch?v=Lc5OM-CpBrQ",
          "author": null,
          "description": "",
          "link": "https://www.youtube.com/watch?v=Lc5OM-CpBrQ",
          "publishedOn": "2021-10-05T17:44:53.000Z",
          "wordCount": null,
          "title": "ヒロシの時事ニュースチャンネルの姉が悲しいツイート！漫画家・忍田鳩子YouTuberニュース 無料 芸能 ニュース"
        },
        {
          "id": "https://www.youtube.com/watch?v=B7valDuXnr0",
          "author": null,
          "description": "",
          "link": "https://www.youtube.com/watch?v=B7valDuXnr0",
          "publishedOn": "2021-10-03T18:06:14.000Z",
          "wordCount": null,
          "title": "予言！2025年7月5日私の見た未来完全版・たつき諒とは？隕石阻止！都市伝説 スピリチュアル Naokiman Show"
        },
        {
          "id": "https://www.youtube.com/watch?v=Szci_rVlYFo",
          "author": null,
          "description": "",
          "link": "https://www.youtube.com/watch?v=Szci_rVlYFo",
          "publishedOn": "2021-10-01T17:17:26.000Z",
          "wordCount": null,
          "title": "【ぼっちの独り言あるある】この動画はすぐに消します！へライザー・ネタ動画・１発ギャグtiktok 雑談 トーク"
        },
        {
          "id": "https://www.youtube.com/watch?v=1n-pceJC45Y",
          "author": null,
          "description": "",
          "link": "https://www.youtube.com/watch?v=1n-pceJC45Y",
          "publishedOn": "2021-09-30T18:21:17.000Z",
          "wordCount": null,
          "title": "マコなり社長の活動休止に思うこと【TTP竹野内社長・りらくる・ビジネス系】まこなり社長  ビジネス系youtuber"
        },
        {
          "id": "https://www.youtube.com/watch?v=vGfNGx_JS1A",
          "author": null,
          "description": "",
          "link": "https://www.youtube.com/watch?v=vGfNGx_JS1A",
          "publishedOn": "2021-09-29T13:48:08.000Z",
          "wordCount": null,
          "title": "【根暗女子あるある】YouTube辞めようって思ってぼっち女子が部屋で愚痴る動画【独り言 お一人様 vlog 日常孤独"
        },
        {
          "id": "https://www.youtube.com/watch?v=qyDH-rwFm60",
          "author": null,
          "description": "",
          "link": "https://www.youtube.com/watch?v=qyDH-rwFm60",
          "publishedOn": "2021-09-28T14:45:26.000Z",
          "wordCount": null,
          "title": "ヒロシの時事ニュースチャンネル。ご冥福をお祈りします・ありがとうございます 時事問題 ヒロシのプライベートチャンネル"
        },
        {
          "id": "https://www.youtube.com/watch?v=1HDFU7JsNWA",
          "author": null,
          "description": "",
          "link": "https://www.youtube.com/watch?v=1HDFU7JsNWA",
          "publishedOn": "2021-09-27T20:05:59.000Z",
          "wordCount": null,
          "title": "ロン毛帰国の小室圭さんにチャンネル８橋下徹・梅沢富美男・谷原章介・お祝いの手のひら返し・芸能 ニュース  小室佳代 結婚"
        },
        {
          "id": "https://www.youtube.com/watch?v=dCYW_-BJk5A",
          "author": null,
          "description": "",
          "link": "https://www.youtube.com/watch?v=dCYW_-BJk5A",
          "publishedOn": "2021-09-24T19:06:52.000Z",
          "wordCount": null,
          "title": "削除覚悟【重要な話あるある】ぼっち独り言怒られて動画消しました。副業YouTuber・学生YouTuberの根性論雑談"
        }
      ]
    },
    {
      "title": "ASCII.jp － トップ",
      "feedUrl": "https://ascii.jp/rss.xml",
      "siteUrl": "https://ascii.jp/1/",
      "articles": [
        {
          "id": "https://ascii.jp/elem/000/004/072/4072253/?rss",
          "author": null,
          "description": "世界最先端のテクノロジー情報をお届けするグローバルメディア「MITテクノロジーレビュー」から、ビジネスに役立つ注目のテック企業の最新動向、イノベーションにつながる最新の研究内容をピックアップして紹介します。",
          "link": "https://ascii.jp/elem/000/004/072/4072253/?rss",
          "publishedOn": "2021-10-19T01:10:00.000Z",
          "wordCount": 575,
          "title": "神経科学で解明「記憶」の疑問5つ／ひっそりと浸透する「AI声優」"
        },
        {
          "id": "https://ascii.jp/elem/000/004/070/4070787/?rss",
          "author": null,
          "description": "音声SNSアプリケーション「moneep」（モニープ）を運営するmoneepは2021年9月10日、アプリ上でランダムなユーザーからモーニングコールを受け取ったり、モーニングコールをかけられるランダムマッチ機能をiOS版、Android版にて実装したと発表。",
          "link": "https://ascii.jp/elem/000/004/070/4070787/?rss",
          "publishedOn": "2021-10-19T01:10:00.000Z",
          "wordCount": 578,
          "title": "モーニングコールアプリ「moneep」、ランダムな誰かにモーニングコールがつながるランダムマッチ機能を実装"
        },
        {
          "id": "https://ascii.jp/elem/000/004/072/4072406/?rss",
          "author": null,
          "description": "アップルはMacBook Proを「M1 Pro」「M1 Max」と名付けられた新チップの搭載で刷新した。",
          "link": "https://ascii.jp/elem/000/004/072/4072406/?rss",
          "publishedOn": "2021-10-19T00:25:00.000Z",
          "wordCount": 415,
          "title": "超強力チップ「M1 Pro」「M1 Max」で、大幅パワーアップの新MacBook Proがついに発表"
        },
        {
          "id": "https://ascii.jp/elem/000/004/072/4072415/?rss",
          "author": null,
          "description": "【CyCraft Japan】本日開催！CODE BLUE に登壇情報及びイベントのご案内",
          "link": "https://ascii.jp/elem/000/004/072/4072415/?rss",
          "publishedOn": "2021-10-19T00:00:00.000Z",
          "wordCount": 652,
          "title": "【CyCraft Japan】本日開催！CODE BLUE に登壇情報及びイベントのご案内"
        },
        {
          "id": "https://ascii.jp/elem/000/004/072/4072414/?rss",
          "author": null,
          "description": "「SlackやTeams、Chatworkのメッセージを統合」「部門毎のクラウド化がDXを阻害」マジセミ 10/19～10/29までのウェビナー番組表を更新",
          "link": "https://ascii.jp/elem/000/004/072/4072414/?rss",
          "publishedOn": "2021-10-19T00:00:00.000Z",
          "wordCount": 601,
          "title": "「SlackやTeams、Chatworkのメッセージを統合」「部門毎のクラウド化がDXを阻害」マジセミ 10/19～10/29までのウェビナー番組表を更新"
        },
        {
          "id": "https://ascii.jp/elem/000/004/072/4072413/?rss",
          "author": null,
          "description": "オンライン商談自動化ツール「アンプトーク」Dialpad（IP電話）と連携",
          "link": "https://ascii.jp/elem/000/004/072/4072413/?rss",
          "publishedOn": "2021-10-19T00:00:00.000Z",
          "wordCount": 684,
          "title": "オンライン商談自動化ツール「アンプトーク」Dialpad（IP電話）と連携"
        },
        {
          "id": "https://ascii.jp/elem/000/004/071/4071866/?rss",
          "author": null,
          "description": "アメリカの10代は意外にもTwitterを使っていない。代わりにSnapchatの支持率が日本と比べて非常に高い。",
          "link": "https://ascii.jp/elem/000/004/071/4071866/?rss",
          "publishedOn": "2021-10-19T00:00:00.000Z",
          "wordCount": 241,
          "title": "アメリカの10代はTwitterとFBガン無視!?　インスタとスナチャに夢中"
        },
        {
          "id": "https://ascii.jp/elem/000/004/072/4072405/?rss",
          "author": null,
          "description": "アップルは、第3世代となるAirPodsを発表。Apple H1チップを搭載し、新たに空間オーディオに対応した。価格は2万3800円。すでに注文を受け付けており、26日に販売が開始される。",
          "link": "https://ascii.jp/elem/000/004/072/4072405/?rss",
          "publishedOn": "2021-10-18T23:00:00.000Z",
          "wordCount": 372,
          "title": "第3世代となったAirPodsの新モデルは空間オーディオ対応で登場　価格は2万3800円"
        },
        {
          "id": "https://ascii.jp/elem/000/004/071/4071543/?rss",
          "author": null,
          "description": "Microsoft Azureの設計運用ベストプラクティスを紹介していく本連載。今回は「IDとアクセス管理」をテーマに、ベストプラクティスを考えていく。「Cloud Adoption Framework」「Well-Architected Framework」といったフレームワークによる整理、Azure ADや他のセキュリティサービスの機能を用いた実装などを紹介する。",
          "link": "https://ascii.jp/elem/000/004/071/4071543/?rss",
          "publishedOn": "2021-10-18T23:00:00.000Z",
          "wordCount": 348,
          "title": "Azureにおける「IDとアクセス管理」のベストプラクティス"
        },
        {
          "id": "https://ascii.jp/elem/000/004/072/4072404/?rss",
          "author": null,
          "description": "アップルは、Siri搭載のスマートスピーカー「HomePod mini」に新色となるイエロー、オレンジ、ブルーの3色を追加。11月に1万1880円で販売を開始する予定。",
          "link": "https://ascii.jp/elem/000/004/072/4072404/?rss",
          "publishedOn": "2021-10-18T22:40:00.000Z",
          "wordCount": 364,
          "title": "アップルのスマートスピーカー、HomePod miniに明るい3色追加"
        },
        {
          "id": "https://ascii.jp/elem/000/004/072/4072397/?rss",
          "author": null,
          "description": "丸亀製麺の一部店舗限定で「担々まぜ釜玉うどん」がスタート。",
          "link": "https://ascii.jp/elem/000/004/072/4072397/?rss",
          "publishedOn": "2021-10-18T22:00:00.000Z",
          "wordCount": 375,
          "title": "【本日発売】丸亀製麺「担々まぜ釜玉うどん」"
        },
        {
          "id": "https://ascii.jp/elem/000/004/072/4072402/?rss",
          "author": null,
          "description": "深層学習モデルは内部で何が起こっているのかが明らかにならない「ブラック・ボックス」であり、情報は漏れない。こうした一般的な考え方に疑問を投げかける研究成果が発表されている。",
          "link": "https://ascii.jp/elem/000/004/072/4072402/?rss",
          "publishedOn": "2021-10-18T21:59:26.000Z",
          "wordCount": 508,
          "title": "「実在しない顔」は実在しない？ AIが作った架空の顔を巻き戻す"
        },
        {
          "id": "https://ascii.jp/elem/000/004/072/4072403/?rss",
          "author": null,
          "description": "米国の合成生物学企業であるギンコ・バイオワークスが9月に上場した。生物学界のインテルになると喧伝し、巧みなストーリーで投資家を熱狂させているギンコは、実際にどんな成果を残し、何を目指しているのか。",
          "link": "https://ascii.jp/elem/000/004/072/4072403/?rss",
          "publishedOn": "2021-10-18T21:44:12.000Z",
          "wordCount": 509,
          "title": "合成生物学のユニコーン 「ギンコ」が描く未来に 2兆円の価値はあるか？"
        },
        {
          "id": "https://ascii.jp/elem/000/004/072/4072401/?rss",
          "author": null,
          "description": "アップルは、音楽配信サービス「Apple Music」に新たなサブスクリプションである「Apple Music Voiceプラン」を発表。",
          "link": "https://ascii.jp/elem/000/004/072/4072401/?rss",
          "publishedOn": "2021-10-18T19:30:00.000Z",
          "wordCount": 367,
          "title": "Apple Musicに最も安価な「Voiceプラン」を追加　Siriでの操作が前提で月480円"
        },
        {
          "id": "https://ascii.jp/elem/000/004/072/4072233/?rss",
          "author": null,
          "description": "1万円でもノイキャン対応！ 買いの完全ワイヤレスイヤフォンとWindows 11搭載PCがわかった！",
          "link": "https://ascii.jp/elem/000/004/072/4072233/?rss",
          "publishedOn": "2021-10-18T15:00:00.000Z",
          "wordCount": 606,
          "title": "週刊アスキー No.1357(2021年10月19日発行)"
        },
        {
          "id": "https://ascii.jp/elem/000/004/072/4072271/?rss",
          "author": null,
          "description": "車のなかで家電製品が使える100V×2口に加えてUSB×2ポート出力も備えるカーインバーター「INOVA カクバーター USB PD搭載 カーインバーター（3R-IBT01）」販売中。",
          "link": "https://ascii.jp/elem/000/004/072/4072271/?rss",
          "publishedOn": "2021-10-18T13:00:00.000Z",
          "wordCount": 368,
          "title": "車にお手軽コンセント！ 小型カーインバーター「カクバーター」"
        },
        {
          "id": "https://ascii.jp/elem/000/004/072/4072070/?rss",
          "author": null,
          "description": "富士通の直販サイト「富士通 WEB MART」では最新モデルを対象にセールを開催中。",
          "link": "https://ascii.jp/elem/000/004/072/4072070/?rss",
          "publishedOn": "2021-10-18T13:00:00.000Z",
          "wordCount": 218,
          "title": "約736gの超軽量ノート「LIFEBOOK WU2/E3」が、Core i3搭載で9万8656円！"
        },
        {
          "id": "https://ascii.jp/elem/000/004/072/4072270/?rss",
          "author": null,
          "description": "アスキーストアでは、PCスタンドとして使えるだけでなく、引き出し式のマウスパッドも装備するため膝の上で使う時にも快適な「マウスパッド搭載PCケース」を販売中。",
          "link": "https://ascii.jp/elem/000/004/072/4072270/?rss",
          "publishedOn": "2021-10-18T12:00:00.000Z",
          "wordCount": 350,
          "title": "膝の上で使う時にも便利な引き出し式のマウスパッド内蔵！ 「マウスパッド搭載PCケース」"
        },
        {
          "id": "https://ascii.jp/elem/000/004/072/4072048/?rss",
          "author": null,
          "description": "デルは、「Inspiron 15 3000」を値引きして販売している。",
          "link": "https://ascii.jp/elem/000/004/072/4072048/?rss",
          "publishedOn": "2021-10-18T12:00:00.000Z",
          "wordCount": 216,
          "title": "Windows 11搭載15.6型ノート「Inspiron 15 3000」が、デル直販サイトで5万2273円！"
        },
        {
          "id": "https://ascii.jp/elem/000/004/072/4072045/?rss",
          "author": null,
          "description": "デルは、15.6型のゲーミングノートパソコン「New Dell G15」がお得に購入できるキャンペーンを実施中。",
          "link": "https://ascii.jp/elem/000/004/072/4072045/?rss",
          "publishedOn": "2021-10-18T12:00:00.000Z",
          "wordCount": 212,
          "title": "GeForce RTX 3050 Ti搭載、15.6型ゲームノート「New Dell G15」が13万円台！"
        },
        {
          "id": "https://ascii.jp/elem/000/004/072/4072269/?rss",
          "author": null,
          "description": "5ヵ所にグラフェンヒーターを内蔵してわずか10秒で暖まるヒーター内蔵ベスト「洗える!ヒーターベスト」。",
          "link": "https://ascii.jp/elem/000/004/072/4072269/?rss",
          "publishedOn": "2021-10-18T11:00:00.000Z",
          "wordCount": 352,
          "title": "5か所のヒーターで10秒速暖！ 手で洗えるグラフェンヒーター内蔵ベスト"
        },
        {
          "id": "https://ascii.jp/elem/000/004/072/4072258/?rss",
          "author": null,
          "description": "グラビア活動することでも知られる美人プロ雀士の高宮まりさんが、最新DVD「Beautiful Dreams」（発売元：スパイスビジュアル、収録時間：100分、価格：4180円）の発売イベントを10月9日、ソフマップAKIBA パソコン・デジタル館で開催した。",
          "link": "https://ascii.jp/elem/000/004/072/4072258/?rss",
          "publishedOn": "2021-10-18T11:00:00.000Z",
          "wordCount": 555,
          "title": "人気No.1の美人プロ雀士・高宮まり、宮古島でしっとり＆セクシーに魅せる！"
        },
        {
          "id": "https://ascii.jp/elem/000/004/072/4072064/?rss",
          "author": null,
          "description": "富士通の直販サイト「富士通 WEB MART」では最新モデルを対象にセールを開催中。",
          "link": "https://ascii.jp/elem/000/004/072/4072064/?rss",
          "publishedOn": "2021-10-18T11:00:00.000Z",
          "wordCount": 228,
          "title": "Core i7-1165G7、1TB SSD搭載で15万円台！　「LIFEBOOK AH77/E3」がお買い得"
        },
        {
          "id": "https://ascii.jp/elem/000/004/072/4072383/?rss",
          "author": null,
          "description": "スクウェア・エニックスは、2021年10月26日に正式サービス開始を予定しているスマートフォン向け完全新作RPG『ゲートオブナイトメア』にて、ゲトメア46キャラ＆相棒診断を10月18日に公開した。",
          "link": "https://ascii.jp/elem/000/004/072/4072383/?rss",
          "publishedOn": "2021-10-18T10:50:00.000Z",
          "wordCount": 322,
          "title": "完全新作スマホRPG『ゲートオブナイトメア』でゲトメア46キャラ＆相棒診断を公開！"
        },
        {
          "id": "https://ascii.jp/elem/000/004/071/4071757/?rss",
          "author": null,
          "description": "ASCII STARTUPは2021年11月19日、IoTやハードウェア製品をはじめ、AIやクラウド、ネットワーク関連など、モノと通信に関わる事業者すべてに向けたオンラインでのビジネスカンファレンスイベント「IoT H/W BIZ DAY 2021」を開催する。",
          "link": "https://ascii.jp/elem/000/004/071/4071757/?rss",
          "publishedOn": "2021-10-18T10:00:00.000Z",
          "wordCount": 706,
          "title": "【11/19無料配信】アリババやセーフィーなどを迎えた強力セッションを展開！ IoT H/W BIZ DAY 2021"
        },
        {
          "id": "https://ascii.jp/elem/000/004/072/4072372/?rss",
          "author": null,
          "description": "2021年10月18日、コロプラはスマートフォン向けゲーム『ユージェネ』にて、ハーフアニバーサリーを記念した特別な#ライブを10月19日～21日に開催すると発表した。ハーブアニバーサリーを記念したキャンペーンも開催している。",
          "link": "https://ascii.jp/elem/000/004/072/4072372/?rss",
          "publishedOn": "2021-10-18T10:00:00.000Z",
          "wordCount": 345,
          "title": "『ユージェネ』ハーフアニバーサリー記念#ライブを19日～21日の3日間で開催！"
        },
        {
          "id": "https://ascii.jp/elem/000/004/072/4072371/?rss",
          "author": null,
          "description": "ASUSは対象の「ガンダムコラボ商品」購入でマウスパッドまたはTシャツをプレゼントを開催した。",
          "link": "https://ascii.jp/elem/000/004/072/4072371/?rss",
          "publishedOn": "2021-10-18T10:00:00.000Z",
          "wordCount": 317,
          "title": "ASUS、「ガンダムコラボ商品」購入でマウスパッドまたはTシャツをプレゼント"
        },
        {
          "id": "https://ascii.jp/elem/000/004/072/4072268/?rss",
          "author": null,
          "description": "さっと取り出せるホルスター型スマホケース「FRUH（フリュー） ホルスタースタイル牛革スマホケース」を60％で販売中。",
          "link": "https://ascii.jp/elem/000/004/072/4072268/?rss",
          "publishedOn": "2021-10-18T10:00:00.000Z",
          "wordCount": 356,
          "title": "スーツにも合う！ ホルスタースタイルの牛革スマホケースが今なら60％オフで買える！！"
        },
        {
          "id": "https://ascii.jp/elem/000/004/072/4072257/?rss",
          "author": null,
          "description": "身長168cmのスレンダー美女がデビュー。18代目「ミニスカポリス」の水谷彩咲（みずたに・あやさ）さんが、1st DVD「Smile Beauty」（発売元：ラインコミュニケーションズ、収録時間：128分、価格：4180円）の発売記念イベントを10月3日、ソフマップAKIBA パソコン・デジタル館で開催した。",
          "link": "https://ascii.jp/elem/000/004/072/4072257/?rss",
          "publishedOn": "2021-10-18T10:00:00.000Z",
          "wordCount": 557,
          "title": "1stにしては攻めている!?　現役ミニスカポリス・水谷彩咲が待望のDVDデビュー"
        },
        {
          "id": "https://ascii.jp/elem/000/004/072/4072370/?rss",
          "author": null,
          "description": "ルネサス エレクトロニクス製RZ/VシリーズのAIチップを搭載した次世代型IoTゲートウェイ。録画装置でありながら、低消費電力の画像AI機能を備える。",
          "link": "https://ascii.jp/elem/000/004/072/4072370/?rss",
          "publishedOn": "2021-10-18T09:30:00.000Z",
          "wordCount": 602,
          "title": "アムニモ、低電力の画像AI機能を搭載した録画装置「AIエッジゲートウェイ」"
        }
      ]
    },
    {
      "title": "ITmedia NEWS 最新記事一覧",
      "feedUrl": "https://rss.itmedia.co.jp/rss/2.0/news_bursts.xml",
      "siteUrl": "https://www.itmedia.co.jp/news/",
      "articles": [
        {
          "id": "https://www.itmedia.co.jp/news/articles/2110/19/news099.html",
          "author": null,
          "description": "米地上放送局運営大手のSinclair Broadcast Groupはランサムウェア攻撃を受けたと発表した。前日朝から傘下の一部の放送局でニュースなどが放映できなかった。本稿執筆現在、まだ調査中だ。",
          "link": "https://www.itmedia.co.jp/news/articles/2110/19/news099.html",
          "publishedOn": "2021-10-19T01:09:00.000Z",
          "wordCount": 151,
          "title": "米テレビ局運営大手Sinclairにランサムウェア攻撃　一部の放送が中断"
        },
        {
          "id": "https://www.itmedia.co.jp/news/articles/2110/19/news097.html",
          "author": null,
          "description": "SNSを通じて児童が性犯罪などに巻き込まれるケースが新潟県内でも増えている。県警はサイバーパトロールを強化するとともに、教員向け研修会を行うなどして歯止めをかけようとしている。",
          "link": "https://www.itmedia.co.jp/news/articles/2110/19/news097.html",
          "publishedOn": "2021-10-19T01:00:00.000Z",
          "wordCount": 151,
          "title": "SNSによる児童の性被害を防げ　新潟県警が強化"
        },
        {
          "id": "https://www.itmedia.co.jp/news/articles/2110/19/news096.html",
          "author": null,
          "description": "銀行のさまざまな手続きをビデオチャット越しにできるアプリケーションを全国で初めて伊予銀行が開発した。アプリを利用すると、客は店舗窓口を訪れているのと同じように、行員の説明を聞きながら選択肢を選んで手続きを進められる。",
          "link": "https://www.itmedia.co.jp/news/articles/2110/19/news096.html",
          "publishedOn": "2021-10-19T01:00:00.000Z",
          "wordCount": 146,
          "title": "銀行手続きがビデオチャットで　伊予銀行がアプリ開発"
        },
        {
          "id": "https://www.itmedia.co.jp/news/articles/2110/19/news095.html",
          "author": null,
          "description": "マイナンバーカードが健康保険証として利用できる仕組みが、全国の医療機関や薬局で順次導入される。普及の後押しとなることが期待されるが、カードを所持することによるメリットは依然少なく、個人情報を政府に監視されるのではとの不安も根強い。",
          "link": "https://www.itmedia.co.jp/news/articles/2110/19/news095.html",
          "publishedOn": "2021-10-19T01:00:00.000Z",
          "wordCount": 144,
          "title": "マイナカード、20日から保険証対応　普及期待も遅れ"
        },
        {
          "id": "https://www.itmedia.co.jp/news/articles/2110/19/news094.html",
          "author": null,
          "description": "台湾積体電路製造が、2022年に日本で新工場の建設に着工し、24年に稼働を始める方針を発表した。ソニーグループと共同で熊本県内に建設し、自動車向けなどの半導体を製造する方向とみられる。",
          "link": "https://www.itmedia.co.jp/news/articles/2110/19/news094.html",
          "publishedOn": "2021-10-19T01:00:00.000Z",
          "wordCount": 141,
          "title": "半導体「日台経済同盟」強化に前進　世界的メーカーTSMCが日本に新工場、政府も支援へ"
        },
        {
          "id": "https://www.itmedia.co.jp/news/articles/2110/19/news037.html",
          "author": null,
          "description": "LINK-Jは「脳は人工的につくれるのか？〜脳の情報処理のフロンティアに挑む」と題したトークイベントを開催。「意識を機械にアップロードする技術」など、最先端の脳研究を披露した。",
          "link": "https://www.itmedia.co.jp/news/articles/2110/19/news037.html",
          "publishedOn": "2021-10-18T23:00:00.000Z",
          "wordCount": 164,
          "title": "「機械の脳」が現実に？　現実味を帯びてきた脳の人工再現――東大研究者たちが講演"
        },
        {
          "id": "https://www.itmedia.co.jp/news/articles/2110/19/news086.html",
          "author": null,
          "description": "Amazonは米国のホリデーシーズンに向けて、15万人を臨時雇用すると発表した。昨年は10万人を雇用した。",
          "link": "https://www.itmedia.co.jp/news/articles/2110/19/news086.html",
          "publishedOn": "2021-10-18T22:59:00.000Z",
          "wordCount": 144,
          "title": "Amazon、年末商戦で15万人を臨時雇用（昨年は10万人）"
        },
        {
          "id": "https://www.itmedia.co.jp/news/articles/2110/19/news085.html",
          "author": null,
          "description": "米Apple初のプロ向けプロセッサ「M1 Pro」「M1 Max」を引っ提げて登場したMacBook Pro。14インチと16インチの2モデル構成になり、2016年から続いたデザインも刷新された。それに併せて、USB Type-Cだけだった端子類がいくつか復活した。",
          "link": "https://www.itmedia.co.jp/news/articles/2110/19/news085.html",
          "publishedOn": "2021-10-18T22:30:00.000Z",
          "wordCount": 213,
          "title": "おかえり「MagSafe」「SDカードスロット」――新型MacBook Proで復活したものと消えたもの"
        },
        {
          "id": "https://www.itmedia.co.jp/news/articles/2110/19/news078.html",
          "author": null,
          "description": "Macにノッチがやってきた。なぜわざわざ。その理由を考えてみた。",
          "link": "https://www.itmedia.co.jp/news/articles/2110/19/news078.html",
          "publishedOn": "2021-10-18T20:37:00.000Z",
          "wordCount": 147,
          "title": "「Macにもノッチ」の理由　新型MacBook Proにあえて投入した切り欠きについて考えた"
        },
        {
          "id": "https://www.itmedia.co.jp/news/articles/2110/19/news076.html",
          "author": null,
          "description": "米Appleは、同社が開発した新チップ「M1 Pro」と「M1 Max」を発表。プロユーザーのために初めて設計されたプロセッサであり、同日に発表した、新型MacBook Proに搭載する。",
          "link": "https://www.itmedia.co.jp/news/articles/2110/19/news076.html",
          "publishedOn": "2021-10-18T19:35:00.000Z",
          "wordCount": 190,
          "title": "Appleが新チップ「M1 Pro」「M1 Max」発表　M1と比べてCPUは70％、GPUは最大4倍高速化"
        },
        {
          "id": "https://www.itmedia.co.jp/news/articles/2110/19/news074.html",
          "author": null,
          "description": "米Appleは10月18日（現地時間）、新型ノートブック「MacBook Pro」の14インチモデル、16インチモデルを発表した。同社が開発した新型プロセッサ「M1 Pro」と「M1 Max」を搭載。デザインも刷新しており、ディスプレイの縁がより薄くなって専有面積が拡大した他、キーボードは「Touch Bar」を廃止。磁力でくっつく「MagSafe 3」、SDカードスロット、HDMI端子などインタフェースも拡充された。",
          "link": "https://www.itmedia.co.jp/news/articles/2110/19/news074.html",
          "publishedOn": "2021-10-18T18:13:00.000Z",
          "wordCount": 201,
          "title": "MacBook Pro 14／16インチ登場　「M1 Pro」「M1 Max」搭載、Touch Bar廃止　約24万円から"
        },
        {
          "id": "https://www.itmedia.co.jp/news/articles/2110/19/news068.html",
          "author": null,
          "description": "米Appleは10月18日（現地時間）、第3世代「AirPods」を発表した。",
          "link": "https://www.itmedia.co.jp/news/articles/2110/19/news068.html",
          "publishedOn": "2021-10-18T17:39:00.000Z",
          "wordCount": 163,
          "title": "「AirPods」に第3世代モデル、空間オーディオ対応　価格は2万3800円　26日から販売"
        },
        {
          "id": "https://www.itmedia.co.jp/news/articles/2110/18/news140.html",
          "author": null,
          "description": "Smart119社が開発した、AIによる脳卒中診断アルゴリズムについての論文が国際科学誌「Scientific Reports」に掲載された。救急患者の容体など情報を基に、脳卒中の中でも「くも膜下出血」「脳梗塞」「脳出血」「主管動脈閉鎖」のいずれに該当するかを判別できるという。",
          "link": "https://www.itmedia.co.jp/news/articles/2110/18/news140.html",
          "publishedOn": "2021-10-18T11:25:00.000Z",
          "wordCount": 145,
          "title": "AIで「くも膜下出血か脳梗塞か？」を即座に判別　千葉市で年度内に実用化へ"
        },
        {
          "id": "https://www.itmedia.co.jp/news/articles/2110/18/news139.html",
          "author": null,
          "description": "中国当局がソニーの中国法人に対し100万元（約1778万円）の罰金を科したと、共同通信が報じた。同社は7月7日に新製品を発表すると中国のSNS「微博」で予告していたが、日中戦争の発端となった盧溝橋事件と同じ日であるとして批判が集まっていた。",
          "link": "https://www.itmedia.co.jp/news/articles/2110/18/news139.html",
          "publishedOn": "2021-10-18T10:41:00.000Z",
          "wordCount": 144,
          "title": "ソニー、中国当局から約1778万円の罰金命令　7月7日の製品発表予告が「中国の威厳損なった」"
        },
        {
          "id": "https://www.itmedia.co.jp/news/articles/2110/18/news118.html",
          "author": null,
          "description": "楽天グループが「楽天ポイント利息」の提供を始めた。楽天IDを持つユーザーが任意のポイントを預け入れると、月利0.009％（年利0.108％）分を還元する。",
          "link": "https://www.itmedia.co.jp/news/articles/2110/18/news118.html",
          "publishedOn": "2021-10-18T09:00:00.000Z",
          "wordCount": 147,
          "title": "「楽天ポイント利息」スタート、年利0.108％で預金を体験　主要共通ポイントでは初"
        },
        {
          "id": "https://www.itmedia.co.jp/news/articles/2110/18/news115.html",
          "author": null,
          "description": "シャープは、バックライトの光源にmini LEDを採用する液晶テレビの新シリーズ「AQUOS XLED」（アクオス エックスレッド）を近日中に発表する。「CEATEC ONLINE 2021」で製品コンセプトを明らかにした。",
          "link": "https://www.itmedia.co.jp/news/articles/2110/18/news115.html",
          "publishedOn": "2021-10-18T08:40:00.000Z",
          "wordCount": 187,
          "title": "mini LED搭載の液晶テレビ「アクオス エックスレッド」、シャープが近日発表"
        },
        {
          "id": "https://www.itmedia.co.jp/news/articles/2110/18/news101.html",
          "author": null,
          "description": "ノーリツは18日、バンダイとのコラボレーションにより音声案内や音楽が流れる給湯器リモコンのカプセル玩具が登場すると発表した。",
          "link": "https://www.itmedia.co.jp/news/articles/2110/18/news101.html",
          "publishedOn": "2021-10-18T06:25:00.000Z",
          "wordCount": 144,
          "title": "「おふろがわきました」　ノーリツの給湯器リモコンがガシャポンに　音声案内を再現"
        },
        {
          "id": "https://www.itmedia.co.jp/news/articles/2110/18/news097.html",
          "author": null,
          "description": "Teslaに乗り始めた山崎潤一郎さんが初の長距離ドライブ。なぜここまで燃費ならぬ電費が安いのか。その仕組みを明かします。",
          "link": "https://www.itmedia.co.jp/news/articles/2110/18/news097.html",
          "publishedOn": "2021-10-18T05:33:00.000Z",
          "wordCount": 140,
          "title": "Teslaでの長距離ドライブ、820km走って電費1000円いかないカラクリ"
        },
        {
          "id": "https://www.itmedia.co.jp/news/articles/2110/18/news093.html",
          "author": null,
          "description": "XR技術を使ったサービスを手掛けるPocket RDは、同社が提供する3Dアバター生成サービス「AVATARIUM」で「名探偵コナン」のコラボレーションアバターを実装。31日まで開催するバーチャル渋谷のハロウィーンイベントで利用できる。",
          "link": "https://www.itmedia.co.jp/news/articles/2110/18/news093.html",
          "publishedOn": "2021-10-18T05:19:00.000Z",
          "wordCount": 155,
          "title": "誰でもコナンや安室透になれる　バーチャル渋谷で使える「名探偵コナン」コラボアバター"
        },
        {
          "id": "https://www.itmedia.co.jp/news/articles/2110/18/news073.html",
          "author": null,
          "description": "すかいらーくホールディングスが、猫のような見た目が特徴の配膳ロボット「BellaBot」を導入し、2022年末までに「ガスト」「しゃぶ葉」など約2000店舗に配備する。感染症対策やスタッフの業務削減が目的という。",
          "link": "https://www.itmedia.co.jp/news/articles/2110/18/news073.html",
          "publishedOn": "2021-10-18T02:54:00.000Z",
          "wordCount": 147,
          "title": "“ネコミミ配膳ロボット”すかいらーくが導入　ガストやしゃぶ葉など約2000店に配備"
        },
        {
          "id": "https://www.itmedia.co.jp/news/articles/2110/18/news071.html",
          "author": null,
          "description": "テレビアニメ「機動戦士ガンダム」などで知られるサンライズは18日、本社を杉並区にあるビルに本社を移転すると発表した。新オフィスは「ホワイトベース」と名付ける。",
          "link": "https://www.itmedia.co.jp/news/articles/2110/18/news071.html",
          "publishedOn": "2021-10-18T02:32:00.000Z",
          "wordCount": 151,
          "title": "新オフィスは「ホワイトベース」　サンライズが本社移転"
        },
        {
          "id": "https://www.itmedia.co.jp/news/articles/2110/18/news061.html",
          "author": null,
          "description": "メタバース構築に注力するFacebookは、欧州でメタバース関連の人材を1万人採用する計画を発表した。メタバース構築計画の中心を欧州に置くとしている。",
          "link": "https://www.itmedia.co.jp/news/articles/2110/18/news061.html",
          "publishedOn": "2021-10-18T00:40:00.000Z",
          "wordCount": 155,
          "title": "Facebook、メタバース人材を欧州で1万人雇用する計画"
        },
        {
          "id": "https://www.itmedia.co.jp/news/articles/2110/18/news057.html",
          "author": null,
          "description": "Squareのジャック・ドーシーCEOは、ビットコインマイニング端末を開発するとツイートした。誰もが手軽にマイニングできる端末を目指す。シリコンレベルから開発するとしている。",
          "link": "https://www.itmedia.co.jp/news/articles/2110/18/news057.html",
          "publishedOn": "2021-10-17T23:27:00.000Z",
          "wordCount": 146,
          "title": "SquareのドーシーCEO、ビットコインマイニング専用端末を開発するとツイート"
        },
        {
          "id": "https://www.itmedia.co.jp/news/articles/2110/18/news056.html",
          "author": null,
          "description": "Facebook広告の詐欺商品に引っ掛かってしまった小寺信良さんはどう対応したか。",
          "link": "https://www.itmedia.co.jp/news/articles/2110/18/news056.html",
          "publishedOn": "2021-10-17T23:19:00.000Z",
          "wordCount": 142,
          "title": "分かりやすい詐欺に引っ掛かったがリカバーした話"
        },
        {
          "id": "https://www.itmedia.co.jp/news/articles/2110/18/news047.html",
          "author": null,
          "description": "異なる背景シーンに合成するときに問題となる照明の処理。これをリアルに合成する手法。",
          "link": "https://www.itmedia.co.jp/news/articles/2110/18/news047.html",
          "publishedOn": "2021-10-17T23:00:00.000Z",
          "wordCount": 143,
          "title": "合成背景に人が溶け込むよう照明を調節する技術　Googleが開発"
        },
        {
          "id": "https://www.itmedia.co.jp/news/articles/2110/18/news052.html",
          "author": null,
          "description": "最高裁第1小法廷は、運営するWebサイトに、閲覧者のPCを暗号資産のマイニングに無断利用するプログラムを設置したとして罪に問われた男性の上告審弁論を12月9日に開くと決めた。罰金10万円とした二審東京高裁判決が見直される可能性がある。",
          "link": "https://www.itmedia.co.jp/news/articles/2110/18/news052.html",
          "publishedOn": "2021-10-17T22:00:00.000Z",
          "wordCount": 139,
          "title": "Coinhive裁判、有罪見直しか　12月に最高裁弁論"
        },
        {
          "id": "https://www.itmedia.co.jp/news/articles/2110/18/news051.html",
          "author": null,
          "description": "30の国と地域でサイバー攻撃対策を話し合う国際会議が開催され、ランサムウェアを使ったサイバー攻撃が「グローバルな安全保障上の脅威だ」との認識で一致。各国間の情報共有を進め、不法な資金移動の取り締まりなどで協力を深める方向になった。",
          "link": "https://www.itmedia.co.jp/news/articles/2110/18/news051.html",
          "publishedOn": "2021-10-17T22:00:00.000Z",
          "wordCount": 140,
          "title": "サイバー攻撃は「世界の安保脅威」　日米欧30カ国　情報共有や資金遮断で協力、中露対抗へ"
        },
        {
          "id": "https://www.itmedia.co.jp/news/articles/2110/18/news049.html",
          "author": null,
          "description": "総務省は、郵便局の持つ個人情報の活用に当たっての注意点や活用事例を議論する有識者会議の初会合を開催した。今後、関係省庁や有識者、日本郵政の担当者らで、個人情報保護法などに抵触しない活用方法を探り、情報活用のガイドラインを改正する。",
          "link": "https://www.itmedia.co.jp/news/articles/2110/18/news049.html",
          "publishedOn": "2021-10-17T22:00:00.000Z",
          "wordCount": 137,
          "title": "郵便データ活用初会合　「社会から懸念にも配慮を」"
        },
        {
          "id": "https://www.itmedia.co.jp/news/articles/2110/17/news022.html",
          "author": null,
          "description": "ゲーム配信サービス「Steam」では暗号資産やNFTを交換できるゲームを禁止する。提供元のValveが開発者向け文書の禁止コンテンツ項目に文言を追加した。これを受け、EpicのCEOが自社アプリストアはブロックチェーンを歓迎するとツイートした。",
          "link": "https://www.itmedia.co.jp/news/articles/2110/17/news022.html",
          "publishedOn": "2021-10-16T22:47:00.000Z",
          "wordCount": 164,
          "title": "Steamではブロックチェーン採用ゲーム禁止　Valveが規約に文言追加"
        },
        {
          "id": "https://www.itmedia.co.jp/news/articles/2110/16/news047.html",
          "author": null,
          "description": "ポケモンGOで15日、恒例のハロウィンイベントが始まりました。しかし新実装の「ヤドキング（ガラルのすがた）」に不具合が発生しています。",
          "link": "https://www.itmedia.co.jp/news/articles/2110/16/news047.html",
          "publishedOn": "2021-10-16T05:30:00.000Z",
          "wordCount": 154,
          "title": "ポケモンGO、「ガラルヤドキング」の進化に不具合　ハロウィンイベントで新実装【修正済み】"
        },
        {
          "id": "https://www.itmedia.co.jp/news/articles/2110/16/news044.html",
          "author": null,
          "description": "買って試さなければ分からないことはある。そのために60km走ってきた。",
          "link": "https://www.itmedia.co.jp/news/articles/2110/16/news044.html",
          "publishedOn": "2021-10-16T03:33:00.000Z",
          "wordCount": 153,
          "title": "Apple Watch Series 7は自転車「サイコン」の代わりになる？　買って走って分かったこと"
        },
        {
          "id": "https://www.itmedia.co.jp/news/articles/2110/16/news037.html",
          "author": null,
          "description": "MicrosoftはE3で予告した「Xbox Series X」にそっくりなミニ冷蔵庫「Xbox Mini Fridge」を本当にホリデーシーズンに発売すると発表した。米国での販売価格は99.99ドル。「各国の規制当局の承認を待っている」。",
          "link": "https://www.itmedia.co.jp/news/articles/2110/16/news037.html",
          "publishedOn": "2021-10-15T23:13:00.000Z",
          "wordCount": 193,
          "title": "Microsoft、「Xbox Series X」そっくりなミニ冷蔵庫を100ドルで今冬発売"
        },
        {
          "id": "https://www.itmedia.co.jp/news/articles/2110/15/news161.html",
          "author": null,
          "description": "10月14日に発生したNTTドコモ通信障害。同社は10月15日に記者会見を開き、加入者や位置情報データを管理する「加入者／位置情報サーバ」の新設備への移行作業が原因であったと謝罪した。",
          "link": "https://www.itmedia.co.jp/news/articles/2110/15/news161.html",
          "publishedOn": "2021-10-15T12:32:00.000Z",
          "wordCount": 161,
          "title": "12時間に及ぶ通信障害はなぜ起きたのか、ドコモの“輻輳”が長引いたワケ"
        },
        {
          "id": "https://www.itmedia.co.jp/news/articles/2110/15/news162.html",
          "author": null,
          "description": "アルバイトマッチングサービスを手掛ける「タイミー」の取締役COOに、元ディー・エヌ・エーの守安功氏が就任する。",
          "link": "https://www.itmedia.co.jp/news/articles/2110/15/news162.html",
          "publishedOn": "2021-10-15T12:31:00.000Z",
          "wordCount": 143,
          "title": "元DeNA代表の守安氏、バイトマッチング「タイミー」の取締役COOに就任"
        },
        {
          "id": "https://www.itmedia.co.jp/news/articles/2110/15/news158.html",
          "author": null,
          "description": "米Slack Technologiesの日本法人Slack Japanが解散することが官報で分かった。米salesforce.comの日本法人であるセールスフォース・ドットコムが吸収合併し、権利義務を承継するという。",
          "link": "https://www.itmedia.co.jp/news/articles/2110/15/news158.html",
          "publishedOn": "2021-10-15T11:08:00.000Z",
          "wordCount": 161,
          "title": "Slack Japan解散へ　セールスフォース・ドットコムが吸収合併"
        },
        {
          "id": "https://www.itmedia.co.jp/news/articles/2110/15/news157.html",
          "author": null,
          "description": "ユニクロは15日、衣類のリユースを進める取り組み「RE.UNIQLO」の一環として、使用済みの「ヒートテックインナー」や「ダウンウェア」を店頭で回収し、代わりにデジタルクーポンを付与するキャンペーンを始めた。",
          "link": "https://www.itmedia.co.jp/news/articles/2110/15/news157.html",
          "publishedOn": "2021-10-15T10:48:00.000Z",
          "wordCount": 150,
          "title": "使用済み「ヒートテックインナー」持ち込みで最大1000円分のクーポン付与　ユニクロ全店で回収キャンペーン"
        },
        {
          "id": "https://www.itmedia.co.jp/news/articles/2110/15/news150.html",
          "author": null,
          "description": "日本マイクロソフトが、JR東日本にIaaS「Microsoft Azure」を提供したと発表した。JR東はバスツアーの検索・予約サービス「BUSKIP」（バスキップ）の提供基盤にAzureを採用。PaaS機能などを活用し、予定通りのリリースに成功したという。",
          "link": "https://www.itmedia.co.jp/news/articles/2110/15/news150.html",
          "publishedOn": "2021-10-15T09:26:00.000Z",
          "wordCount": 159,
          "title": "JR東、バスツアー“相乗り”サービスにAzure採用　MaaS手掛けるSIerと短期開発"
        },
        {
          "id": "https://www.itmedia.co.jp/news/articles/2110/15/news126.html",
          "author": null,
          "description": "NTTドコモは、10月14日に全国で発生した通信障害について記者会見を開いた。同社の田村穂積副社長は「大変ご迷惑をおかけし、深く反省している」と謝罪した。",
          "link": "https://www.itmedia.co.jp/news/articles/2110/15/news126.html",
          "publishedOn": "2021-10-15T06:26:00.000Z",
          "wordCount": 143,
          "title": "「深く反省している」――ドコモ、14日の通信障害を謝罪"
        },
        {
          "id": "https://www.itmedia.co.jp/news/articles/2110/15/news113.html",
          "author": null,
          "description": "金子総務大臣は10月15日午前の会見にて、NTTドコモの回線で発生した14日の通信障害について「大変遺憾」と発言。同社に原因の究明と速やかな報告を求めた。",
          "link": "https://www.itmedia.co.jp/news/articles/2110/15/news113.html",
          "publishedOn": "2021-10-15T04:47:00.000Z",
          "wordCount": 143,
          "title": "ドコモ通信障害で金子総務大臣「大変遺憾」　原因究明と報告求める"
        },
        {
          "id": "https://www.itmedia.co.jp/news/articles/2110/15/news109.html",
          "author": null,
          "description": "バンダイナムコグループは、11月3日を「サステナブルデー」として動く実物大ガンダムがある「GUNDAM FACTORY YOKOHAMA」の入場を無料にすると発表した。",
          "link": "https://www.itmedia.co.jp/news/articles/2110/15/news109.html",
          "publishedOn": "2021-10-15T04:07:00.000Z",
          "wordCount": 166,
          "title": "動く実物大ガンダム、11月3日は入場無料　ガンプラ無料配布も"
        },
        {
          "id": "https://www.itmedia.co.jp/news/articles/2110/15/news106.html",
          "author": null,
          "description": "米Oracleが、イスラエルの首都・エルサレムにデータセンターを開設する。ミサイルなどの攻撃から施設を守るため、地下に構築するという。",
          "link": "https://www.itmedia.co.jp/news/articles/2110/15/news106.html",
          "publishedOn": "2021-10-15T03:52:00.000Z",
          "wordCount": 214,
          "title": "Oracle、イスラエルに地下データセンター構築へ　ミサイルなどの攻撃から守るため"
        },
        {
          "id": "https://www.itmedia.co.jp/news/articles/2110/15/news099.html",
          "author": null,
          "description": "10月14日午後5時ごろから発生していたNTTドコモの通信障害について、同社は15日午後2時からオンライン記者会見を開くと発表。会見には田村穂積副社長と小林宏ネットワーク本部長、引馬章裕サービス運営部長が出席予定。",
          "link": "https://www.itmedia.co.jp/news/articles/2110/15/news099.html",
          "publishedOn": "2021-10-15T03:23:00.000Z",
          "wordCount": 143,
          "title": "ドコモ、14日の通信障害についてきょう午後2時から会見　副社長らが説明"
        },
        {
          "id": "https://www.itmedia.co.jp/news/articles/2110/15/news098.html",
          "author": null,
          "description": "Clubhouseに「Music Mode」が追加される。“高音質で優れたステレオサウンド”で音楽をブロードキャストできる機能だ。USBマイクやミキサーなどのプロ仕様のオーディオ機器を使うこともできる。",
          "link": "https://www.itmedia.co.jp/news/articles/2110/15/news098.html",
          "publishedOn": "2021-10-15T03:13:00.000Z",
          "wordCount": 147,
          "title": "Clubhouse、高音質ステレオの「ミュージックモード」　外部ミキサー利用も可能"
        },
        {
          "id": "https://www.itmedia.co.jp/news/articles/2110/15/news090.html",
          "author": null,
          "description": "Facebookは次世代AI研究プロジェクト「Ego4D」を発表した。世界9カ国の855人が撮影した一人称視点の動画データセットを使い、「人間と同じ様に一人称視点で世界を理解し、世界と関わるAI」を開発する。",
          "link": "https://www.itmedia.co.jp/news/articles/2110/15/news090.html",
          "publishedOn": "2021-10-15T02:24:00.000Z",
          "wordCount": 161,
          "title": "Facebook、次世代AI「Ego4D」開発用一人称視点動画を世界で2200時間分収集"
        },
        {
          "id": "https://www.itmedia.co.jp/news/articles/2110/15/news084.html",
          "author": null,
          "description": "米Snowflakeの日本法人が、クラウド型のデータウェアハウスサービス「Snowflake」（スノーフレイク）について、IaaS「Microsoft Azure」の東日本リージョン上で動作するバージョンの提供を始めた。",
          "link": "https://www.itmedia.co.jp/news/articles/2110/15/news084.html",
          "publishedOn": "2021-10-15T01:47:00.000Z",
          "wordCount": 155,
          "title": "データウェアハウスSaaS「Snowflake」、Azure東日本リージョン対応版を提供開始"
        },
        {
          "id": "https://www.itmedia.co.jp/news/articles/2110/15/news083.html",
          "author": null,
          "description": "10月14日から続いていたNTTドコモの通信障害について、4G／5G回線について完全復旧したと発表した。3G回線についてはまだ繋がりにくい状態が続いており、全面復旧についてはもうしばらくかかる見込み。",
          "link": "https://www.itmedia.co.jp/news/articles/2110/15/news083.html",
          "publishedOn": "2021-10-15T01:38:00.000Z",
          "wordCount": 138,
          "title": "ドコモの通信障害、4G／5Gは完全復旧　3Gは繋がりにくい状況続く"
        },
        {
          "id": "https://www.itmedia.co.jp/news/articles/2110/15/news070.html",
          "author": null,
          "description": "Microsoftが中国版LinkedInを年内に廃止すると発表。2014年から7年間提供してきたが、「非常に困難な運用環境」のため。中国では新たにSNS要素のないジョブアプリ「InJobs」を提供する。",
          "link": "https://www.itmedia.co.jp/news/articles/2110/15/news070.html",
          "publishedOn": "2021-10-14T23:36:00.000Z",
          "wordCount": 142,
          "title": "Microsoft、中国版LinkedInを年内に廃止へ　「コンプライアンス要件の高まりに直面」"
        },
        {
          "id": "https://www.itmedia.co.jp/news/articles/2110/15/news048.html",
          "author": null,
          "description": "機械学習を使い、個人情報に含まれるうそを見破ることが可能になった。",
          "link": "https://www.itmedia.co.jp/news/articles/2110/15/news048.html",
          "publishedOn": "2021-10-14T23:00:00.000Z",
          "wordCount": 148,
          "title": "その個人情報はうそか本当か、AIが判定　4種類のうそのつき方が明らかに"
        },
        {
          "id": "https://www.itmedia.co.jp/news/articles/2110/15/news047.html",
          "author": null,
          "description": "血管を肌のレイヤーに重ねるとリアルになるというテクニックはあるが、それを動きで反映する。",
          "link": "https://www.itmedia.co.jp/news/articles/2110/15/news047.html",
          "publishedOn": "2021-10-14T23:00:00.000Z",
          "wordCount": 143,
          "title": "血流の動きをアバターの顔に反映したら、より人間的になった　Microsoftなどが技術開発"
        },
        {
          "id": "https://www.itmedia.co.jp/news/articles/2110/15/news069.html",
          "author": null,
          "description": "ミュージシャンや文化人、ビジネスの専門家といったパーソナリティーが、スマートフォンで“声のブログ”を配信する「Voicy」が急成長している。GAFAをはじめとする巨大IT企業も相次いで参入している音声にはどんな可能性があるのか聞いてみた。",
          "link": "https://www.itmedia.co.jp/news/articles/2110/15/news069.html",
          "publishedOn": "2021-10-14T22:00:00.000Z",
          "wordCount": 171,
          "title": "日本発の音声サービスで世界を変える　うつむきスマホの生活スタイルにさよなら　Voicy・緒方憲太郎CEO"
        }
      ]
    },
    {
      "title": "Search results for \"yunapota\"",
      "feedUrl": "https://nitter-5jtb6c6pqa-uc.a.run.app/search/rss?f=tweets&q=yunapota",
      "siteUrl": "http://nitter.net/search",
      "articles": [
        {
          "id": "http://nitter.net/yunapota/status/1450234627751219200#m",
          "author": "@yunapota",
          "description": "😍😍😍",
          "link": "http://nitter.net/yunapota/status/1450234627751219200#m",
          "publishedOn": "2021-10-18T22:57:33.000Z",
          "wordCount": 33,
          "title": "R to @mito_kaz: 😍😍😍"
        },
        {
          "id": "http://nitter.net/knock1965/status/1450222659308961793#m",
          "author": "@knock1965",
          "description": "#高橋ユナ  ~lucky one~\n\n#studio \n#photography\n#portrait \n#mimosahouse",
          "link": "http://nitter.net/knock1965/status/1450222659308961793#m",
          "publishedOn": "2021-10-18T22:10:00.000Z",
          "wordCount": 34,
          "title": "RT by @yunapota: #高橋ユナ  ~lucky one~\n\n#studio \n#photography\n#portrait \n#mimosahouse"
        },
        {
          "id": "http://nitter.net/kqqnx218/status/1450090937086922761#m",
          "author": "@kqqnx218",
          "description": "おしまい！😨",
          "link": "http://nitter.net/kqqnx218/status/1450090937086922761#m",
          "publishedOn": "2021-10-18T13:26:35.000Z",
          "wordCount": 37,
          "title": "R to @yunapota: おしまい！😨"
        },
        {
          "id": "http://nitter.net/196805081016/status/1450065826103521283#m",
          "author": "@196805081016",
          "description": "秋はもうずいぶん前から無いですよ",
          "link": "http://nitter.net/196805081016/status/1450065826103521283#m",
          "publishedOn": "2021-10-18T11:46:48.000Z",
          "wordCount": 37,
          "title": "R to @yunapota: 秋はもうずいぶん前から無いですよ"
        },
        {
          "id": "http://nitter.net/fuuchan07040326/status/1450058531797803009#m",
          "author": "@fuuchan07040326",
          "description": "(。´Д⊂)",
          "link": "http://nitter.net/fuuchan07040326/status/1450058531797803009#m",
          "publishedOn": "2021-10-18T11:17:49.000Z",
          "wordCount": 55,
          "title": "R to @yunapota: (。´Д⊂)"
        },
        {
          "id": "http://nitter.net/cats_eye_nekome/status/1450054444201111553#m",
          "author": "@cats_eye_nekome",
          "description": "紅葉🍁を背景に撮影したいです🤗",
          "link": "http://nitter.net/cats_eye_nekome/status/1450054444201111553#m",
          "publishedOn": "2021-10-18T11:01:34.000Z",
          "wordCount": 57,
          "title": "R to @yunapota: 紅葉🍁を背景に撮影したいです🤗"
        },
        {
          "id": "http://nitter.net/nbG98PEzLYoYBRm/status/1450054401591181314#m",
          "author": "@nbG98PEzLYoYBRm",
          "description": "秋の紅葉と綺麗なゆなさんのコラボの写真 見たかった……😎",
          "link": "http://nitter.net/nbG98PEzLYoYBRm/status/1450054401591181314#m",
          "publishedOn": "2021-10-18T11:01:24.000Z",
          "wordCount": 39,
          "title": "R to @yunapota: 秋の紅葉と綺麗なゆなさんのコラボの写真 見たかった……😎"
        },
        {
          "id": "http://nitter.net/kmsn_124/status/1450052972889526275#m",
          "author": "@kmsn_124",
          "description": "ゆな様的にはまだ夏の模様（アイコン）🧎‍♂️🧎‍♂️",
          "link": "http://nitter.net/kmsn_124/status/1450052972889526275#m",
          "publishedOn": "2021-10-18T10:55:44.000Z",
          "wordCount": 37,
          "title": "R to @yunapota: ゆな様的にはまだ夏の模様（アイコン）🧎‍♂️🧎‍♂️"
        },
        {
          "id": "http://nitter.net/gaaaaamin_S63/status/1450051023335161860#m",
          "author": "@gaaaaamin_S63",
          "description": "秋は今年は自粛しててきません",
          "link": "http://nitter.net/gaaaaamin_S63/status/1450051023335161860#m",
          "publishedOn": "2021-10-18T10:47:59.000Z",
          "wordCount": 37,
          "title": "R to @yunapota: 秋は今年は自粛しててきません"
        },
        {
          "id": "http://nitter.net/yunapota/status/1450049792206270464#m",
          "author": "@yunapota",
          "description": "🥲🥲🥲",
          "link": "http://nitter.net/yunapota/status/1450049792206270464#m",
          "publishedOn": "2021-10-18T10:43:05.000Z",
          "wordCount": 59,
          "title": "R to @cats_eye_nekome: 🥲🥲🥲"
        },
        {
          "id": "http://nitter.net/yunapota/status/1450049766671347712#m",
          "author": "@yunapota",
          "description": "😗😗😗",
          "link": "http://nitter.net/yunapota/status/1450049766671347712#m",
          "publishedOn": "2021-10-18T10:42:59.000Z",
          "wordCount": 45,
          "title": "R to @hiroa777: 😗😗😗"
        },
        {
          "id": "http://nitter.net/yunapota/status/1450049718097174537#m",
          "author": "@yunapota",
          "description": "🥶🥶🥶😱😱😱",
          "link": "http://nitter.net/yunapota/status/1450049718097174537#m",
          "publishedOn": "2021-10-18T10:42:48.000Z",
          "wordCount": 45,
          "title": "R to @knock1965: 🥶🥶🥶😱😱😱"
        },
        {
          "id": "http://nitter.net/yunapota/status/1450049686723645443#m",
          "author": "@yunapota",
          "description": "🥶🥶🥶",
          "link": "http://nitter.net/yunapota/status/1450049686723645443#m",
          "publishedOn": "2021-10-18T10:42:40.000Z",
          "wordCount": 45,
          "title": "R to @jassy34aya6: 🥶🥶🥶"
        },
        {
          "id": "http://nitter.net/yunapota/status/1450049624698359808#m",
          "author": "@yunapota",
          "description": "😆😆😆",
          "link": "http://nitter.net/yunapota/status/1450049624698359808#m",
          "publishedOn": "2021-10-18T10:42:25.000Z",
          "wordCount": 45,
          "title": "R to @maryou6504: 😆😆😆"
        },
        {
          "id": "http://nitter.net/yunapota/status/1450049563952254978#m",
          "author": "@yunapota",
          "description": "😂",
          "link": "http://nitter.net/yunapota/status/1450049563952254978#m",
          "publishedOn": "2021-10-18T10:42:11.000Z",
          "wordCount": 58,
          "title": "R to @fuuchan07040326: 😂"
        },
        {
          "id": "http://nitter.net/yunapota/status/1450049536869613570#m",
          "author": "@yunapota",
          "description": "( ˘ •ω• ˘ )",
          "link": "http://nitter.net/yunapota/status/1450049536869613570#m",
          "publishedOn": "2021-10-18T10:42:04.000Z",
          "wordCount": 54,
          "title": "R to @StrayCat_H_C: ( ˘ •ω• ˘ )"
        },
        {
          "id": "http://nitter.net/yunapota/status/1450049497187307524#m",
          "author": "@yunapota",
          "description": "(˙-˙   )(   ˙-˙   )(   ˙-˙)ｷｮﾛｷｮﾛ",
          "link": "http://nitter.net/yunapota/status/1450049497187307524#m",
          "publishedOn": "2021-10-18T10:41:55.000Z",
          "wordCount": 54,
          "title": "R to @mamesans_photo: (˙-˙   )(   ˙-˙   )(   ˙-˙)ｷｮﾛｷｮﾛ"
        },
        {
          "id": "http://nitter.net/yunapota/status/1450049393227296768#m",
          "author": "@yunapota",
          "description": "😂😂😂😂",
          "link": "http://nitter.net/yunapota/status/1450049393227296768#m",
          "publishedOn": "2021-10-18T10:41:30.000Z",
          "wordCount": 45,
          "title": "R to @Fukuyama_GKI: 😂😂😂😂"
        },
        {
          "id": "http://nitter.net/knock1965/status/1450046329065914371#m",
          "author": "@knock1965",
          "description": "😶‍🌫️😶‍🌫️🥶🥶🤣🤣",
          "link": "http://nitter.net/knock1965/status/1450046329065914371#m",
          "publishedOn": "2021-10-18T10:29:20.000Z",
          "wordCount": 48,
          "title": "R to @yunapota: 😶‍🌫️😶‍🌫️🥶🥶🤣🤣"
        },
        {
          "id": "http://nitter.net/mito_kaz/status/1445713053203402759#m",
          "author": "@mito_kaz",
          "description": "",
          "link": "http://nitter.net/mito_kaz/status/1445713053203402759#m",
          "publishedOn": "2021-10-06T11:30:26.000Z",
          "wordCount": 33,
          "title": "RT by @yunapota:"
        }
      ]
    }
  ],
  "cliVersion": "1.11.3"
}